pynetflix/__init__.py
pynetflix/configs.py
pynetflix/main.py
pynetflix/static.py
pynetflix-0.0.3.dist-info/LICENSE
pynetflix-0.0.3.dist-info/METADATA
pynetflix-0.0.3.dist-info/WHEEL
pynetflix-0.0.3.dist-info/entry_points.txt
pynetflix-0.0.3.dist-info/top_level.txt
pynetflix-0.0.3.dist-info/RECORD
